{
  "sections": {
    "homepage_section_bG38N7": {
      "type": "homepage-section",
      "settings": {
      }
    },
    "tabs_UPAUwq": {
      "type": "tabs",
      "blocks": {
        "tab_zUrhfx": {
          "type": "tab",
          "settings": {
            "collection": "best-sellers"
          }
        }
      },
      "block_order": [
        "tab_zUrhfx"
      ],
      "settings": {
        "title": ""
      }
    },
    "homepage_section2_DNUimF": {
      "type": "homepage-section2",
      "settings": {
      }
    }
  },
  "order": [
    "homepage_section_bG38N7",
    "tabs_UPAUwq",
    "homepage_section2_DNUimF"
  ]
}
